<?xml version="1.0" encoding="utf-8"?>
<ODM xmlns:xlink="http://www.w3.org/1999/xlink" xmlns:xsi="http://www.w3.org/2001/XMLSchema-instance" xmlns:dl="http://www.datalabs.com/schema/cdisc/def" xmlns:ds="http://www.w3.org/2000/09/xmldsig#" Description="Form Status" FileType="Transactional" Granularity="SingleSubject" FileOID="cfc9a361-8dd8-4225-85df-1fd464bbf7ff" CreationDateTime="2018-12-26T12:23:46.3957799Z" ODMVersion="1.3.2" Originator="PAREXEL" SourceSystem="DataLabs" SourceSystemVersion="5.7.0" xmlns="http://www.cdisc.org/ns/odm/v1.3">
  <Study OID="Test3210_FoStPsA">
    <GlobalVariables>
      <StudyName>Test3210_FoStPsA</StudyName>
      <StudyDescription>This study will be used for testing of version 4.3</StudyDescription>
      <ProtocolName>20070215</ProtocolName>
    </GlobalVariables>
  </Study>
  <ClinicalData StudyOID="Test3210_FoStPsA" MetaDataVersionOID="200702151.0">
    <SubjectData SubjectKey="ED4002EC-1EF4-4F60-B4BA-A4D920D743ED">
      <SiteRef LocationOID="01-Site" />
      <StudyEventData StudyEventOID="Visit02">
        <Annotation SeqNum="1">
          <Comment>Visit02</Comment>
        </Annotation>
        <FormData FormOID="Form2">
          <AuditRecord>
            <UserRef UserOID="System" />
            <LocationRef LocationOID="01-Site" />
            <DateTimeStamp>2018-12-26T12:23:45.42</DateTimeStamp>
            <ReasonForChange>Unpublished</ReasonForChange>
            <SourceID>60</SourceID>
          </AuditRecord>
          <Annotation SeqNum="1">
            <Comment>Additional Notes:Unpublished (pScript: Unpublish_All_events_Form2)</Comment>
          </Annotation>
        </FormData>
      </StudyEventData>
    </SubjectData>
  </ClinicalData>
</ODM>